AUTHORS.rst
CONTRIBUTING.rst
HISTORY.rst
LICENSE
MANIFEST.in
README.rst
setup.cfg
setup.py
config_edit/__init__.py
config_edit/ssh.py
config_edit.egg-info/PKG-INFO
config_edit.egg-info/SOURCES.txt
config_edit.egg-info/dependency_links.txt
config_edit.egg-info/not-zip-safe
config_edit.egg-info/top_level.txt
docs/Makefile
docs/authors.rst
docs/conf.py
docs/contributing.rst
docs/history.rst
docs/index.rst
docs/installation.rst
docs/make.bat
docs/readme.rst
docs/usage.rst
tests/__init__.py
tests/test_ssh.py