Metadata-Version: 1.1
Name: config-edit
Version: 0.0.1
Summary: Library to work with config files of various applications
Home-page: https://github.com/hamzasheikh/config_edit
Author: Hamza Sheikh
Author-email: code@codeghar.com
License: MIT
Keywords: config_edit
Platform: UNKNOWN
Classifier: Development Status :: 2 - Pre-Alpha
Classifier: Intended Audience :: Developers
Classifier: License :: OSI Approved :: MIT License
Classifier: Natural Language :: English
Classifier: Programming Language :: Python :: 3
Classifier: Programming Language :: Python :: 3.4
Classifier: Programming Language :: Python :: 3.5
